gridsync/__init__.py
gridsync/_version.py
gridsync/cli.py
gridsync/config.py
gridsync/core.py
gridsync/crypto.py
gridsync/desktop.py
gridsync/errors.py
gridsync/filter.py
gridsync/invite.py
gridsync/lock.py
gridsync/monitor.py
gridsync/msg.py
gridsync/news.py
gridsync/preferences.py
gridsync/recovery.py
gridsync/setup.py
gridsync/streamedlogs.py
gridsync/tahoe.py
gridsync/tor.py
gridsync/util.py
gridsync/wormhole_.py
gridsync/gui/__init__.py
gridsync/gui/color.py
gridsync/gui/debug.py
gridsync/gui/font.py
gridsync/gui/history.py
gridsync/gui/invite.py
gridsync/gui/main_window.py
gridsync/gui/menu.py
gridsync/gui/model.py
gridsync/gui/password.py
gridsync/gui/pixmap.py
gridsync/gui/preferences.py
gridsync/gui/share.py
gridsync/gui/status.py
gridsync/gui/systray.py
gridsync/gui/view.py
gridsync/gui/welcome.py
gridsync/gui/widgets.py
gridsync/resources/arrow-right.png
gridsync/resources/checkmark.png
gridsync/resources/close.png
gridsync/resources/cloud-icon.png
gridsync/resources/cloud.png
gridsync/resources/cloud_storage.png
gridsync/resources/config.txt
gridsync/resources/copy.png
gridsync/resources/dots-horizontal-triple.png
gridsync/resources/download.png
gridsync/resources/export.png
gridsync/resources/eye.png
gridsync/resources/globe.png
gridsync/resources/green-plus.png
gridsync/resources/green_checkmark.png
gridsync/resources/gridsync.gif
gridsync/resources/gridsync.png
gridsync/resources/invite.png
gridsync/resources/key.png
gridsync/resources/laptop-with-icon.png
gridsync/resources/laptop.png
gridsync/resources/leastauthority.com.icon
gridsync/resources/lines_dotted.png
gridsync/resources/lines_solid.png
gridsync/resources/mail-envelope-closed.png
gridsync/resources/mail-envelope-open.png
gridsync/resources/notification.png
gridsync/resources/paste.png
gridsync/resources/pixel.png
gridsync/resources/preferences.png
gridsync/resources/question.png
gridsync/resources/share.png
gridsync/resources/star.png
gridsync/resources/sync.gif
gridsync-0.4.3.dist-info/LICENSE
gridsync-0.4.3.dist-info/METADATA
gridsync-0.4.3.dist-info/WHEEL
gridsync-0.4.3.dist-info/entry_points.txt
gridsync-0.4.3.dist-info/top_level.txt
gridsync-0.4.3.dist-info/RECORD
