Metadata-Version: 2.1
Name: gridsync
Version: 0.4.3
Summary: Synchronize local directories with Tahoe-LAFS storage grids.
Home-page: https://github.com/gridsync/gridsync
Author: Christopher R. Wood
License: GPLv3
Keywords: gridsync tahoe-lafs tahoe lafs allmydata-tahoe magic-wormhole
Platform: UNKNOWN
Classifier: Development Status :: 4 - Beta
Classifier: Environment :: MacOS X
Classifier: Environment :: Win32 (MS Windows)
Classifier: Environment :: X11 Applications
Classifier: Environment :: X11 Applications :: Gnome
Classifier: Environment :: X11 Applications :: GTK
Classifier: Environment :: X11 Applications :: KDE
Classifier: Environment :: X11 Applications :: Qt
Classifier: Intended Audience :: End Users/Desktop
Classifier: License :: DFSG approved
Classifier: License :: OSI Approved
Classifier: License :: OSI Approved :: GNU General Public License v3 (GPLv3)
Classifier: Natural Language :: English
Classifier: Operating System :: MacOS :: MacOS X
Classifier: Operating System :: Microsoft :: Windows
Classifier: Operating System :: Microsoft :: Windows :: Windows 7
Classifier: Operating System :: Microsoft :: Windows :: Windows 8
Classifier: Operating System :: Microsoft :: Windows :: Windows 8.1
Classifier: Operating System :: Microsoft :: Windows :: Windows 10
Classifier: Operating System :: POSIX
Classifier: Operating System :: POSIX :: Linux
Classifier: Programming Language :: Python
Classifier: Programming Language :: Python :: 3
Classifier: Programming Language :: Python :: 3.6
Classifier: Programming Language :: Python :: 3.7
Classifier: Programming Language :: Python :: 3.8
Classifier: Programming Language :: Python :: 3 :: Only
Classifier: Topic :: Communications :: File Sharing
Classifier: Topic :: Desktop Environment
Classifier: Topic :: Internet
Classifier: Topic :: Security
Classifier: Topic :: Security :: Cryptography
Classifier: Topic :: System :: Archiving
Classifier: Topic :: System :: Archiving :: Backup
Classifier: Topic :: System :: Archiving :: Mirroring
Classifier: Topic :: System :: Distributed Computing
Classifier: Topic :: System :: Filesystems
Classifier: Topic :: System :: Recovery Tools
Classifier: Topic :: Utilities
Requires-Python: >=3.6, <3.9
Requires-Dist: atomicwrites
Requires-Dist: autobahn
Requires-Dist: humanize
Requires-Dist: hyperlink
Requires-Dist: magic-wormhole
Requires-Dist: PyNaCl (>=1.2.0)
Requires-Dist: PyQt5
Requires-Dist: pyyaml
Requires-Dist: qt5reactor
Requires-Dist: treq
Requires-Dist: twisted[tls]
Requires-Dist: txtorcon
Requires-Dist: zxcvbn
Requires-Dist: distro ; sys_platform != "darwin" and sys_platform != "win32"
